{
    "id": 20,
    "name": "\u91ab\u7642\u80fd\u529b",
    "game_info": "\u76f8\u9130\u7684\u6240\u6709\u55ae\u4f4d\u6bcf\u56de\u5408\u984d\u5916\u56de\u5fa95\u9ede\u751f\u547d\u503c\u3002",
    "prereq_promotions": [
        {
            "name": "\u885d\u64ca\u4e00\u7d1a",
            "url": "https://eyefyre.github.io/civvapi/v1/zh/promotions/shock_i.json"
        },
        {
            "name": "\u64cd\u7df4\u4e00\u7d1a",
            "url": "https://eyefyre.github.io/civvapi/v1/zh/promotions/drill_i.json"
        },
        {
            "name": "\u5075\u5bdf\u4e8c\u7d1a",
            "url": "https://eyefyre.github.io/civvapi/v1/zh/promotions/scouting_ii.json"
        },
        {
            "name": "\u751f\u5b58\u4e8c\u7d1a",
            "url": "https://eyefyre.github.io/civvapi/v1/zh/promotions/survivalism_ii.json"
        }
    ],
    "icon": "https://eyefyre.github.io/civvapi/images/promotion_icons/medic_h.png"
}