{
    "id": 37,
    "name": "Movilidad",
    "game_info": "+1 al Movimiento.",
    "prereq_promotions": [
        {
            "name": "Choque III",
            "url": "https://eyefyre.github.io/civvapi/v1/es/promotions/shock_iii.json"
        },
        {
            "name": "Instrucci\u00f3n III",
            "url": "https://eyefyre.github.io/civvapi/v1/es/promotions/drill_iii.json"
        },
        {
            "name": "Fijaci\u00f3n de objetivos I",
            "url": "https://eyefyre.github.io/civvapi/v1/es/promotions/targeting_i.json"
        },
        {
            "name": "Bombardeo I",
            "url": "https://eyefyre.github.io/civvapi/v1/es/promotions/bombardment_i.json"
        },
        {
            "name": "Asaltante costero I",
            "url": "https://eyefyre.github.io/civvapi/v1/es/promotions/coastal_raider_i.json"
        },
        {
            "name": "Grupo de abordaje I",
            "url": "https://eyefyre.github.io/civvapi/v1/es/promotions/boarding_party_i.json"
        },
        {
            "name": "Manada de lobos I",
            "url": "https://eyefyre.github.io/civvapi/v1/es/promotions/wolfpack_i.json"
        },
        {
            "name": "Cubierta de vuelo I",
            "url": "https://eyefyre.github.io/civvapi/v1/es/promotions/flight_deck_i.json"
        },
        {
            "name": "Recubrimiento de blindaje I",
            "url": "https://eyefyre.github.io/civvapi/v1/es/promotions/armor_plating_i.json"
        }
    ],
    "icon": "https://eyefyre.github.io/civvapi/images/promotion_icons/movilidad_r.png"
}