{
    "id": 55,
    "name": "Incursi\u00f3n",
    "game_info": "Puede hacer una intercepci\u00f3n adicional por turno.",
    "prereq_promotions": [
        {
            "name": "Intercepci\u00f3n II",
            "url": "https://eyefyre.github.io/civvapi/v1/es/promotions/interception_ii.json"
        },
        {
            "name": "Lucha a\u00e9rea II",
            "url": "https://eyefyre.github.io/civvapi/v1/es/promotions/dogfighting_ii.json"
        }
    ],
    "icon": "https://eyefyre.github.io/civvapi/images/promotion_icons/incursi\u00f3n_a.png"
}