{
    "id": 36,
    "name": "\ud504\ub85c\ub77c",
    "production_cost": 1060,
    "game_info": "\uc804\uc81c\uc815\uce58\uac00 \ud544\uc694\ud569\ub2c8\ub2e4. \ud589\ubcf5\uc774 2 \uc99d\uac00\ud558\uba70, \ucc44\ud0dd\ud55c \uc815\ucc45 2\uac1c\ub9c8\ub2e4 \ucd94\uac00\ub85c \ud589\ubcf5\uc744 1\uc529 \ub354 \uc5bb\uc2b5\ub2c8\ub2e4. \uc0ac\ud68c \uc815\ucc45 1\uac1c\ub97c \uc989\uc2dc \ucc44\ud0dd\ud560 \uc218 \uc788\uc2b5\ub2c8\ub2e4. \ud574\uc548 \ub3c4\uc2dc\uc5d0\ub9cc \uac74\uc124\ud560 \uc218 \uc788\uc2b5\ub2c8\ub2e4.",
    "strategy": null,
    "historical_info": "\ud504\ub85c\ub77c\ub294 \ubc1c\ud2b8 \ud574 \ub93c\uac90 \uc12c\uc5d0 \ud574\ubcc0 \ud734\uc591\uc9c0\ub85c \uc9c0\uc5b4\uc84c\ub2e4. \uc774 \uac70\ub300\ud55c \ubcf5\ud569\ub2e8\uc9c0\ub294 \ub3c5\uc77c\uc778 \ub178\ub3d9\uc790\ub4e4\uc5d0\uac8c \uac78\ub9de\uc740 \ud734\uc591\uc2dc\uc124\uc774 \ub420 \uc608\uc815\uc774\uc5c8\ub2e4. \ubcf8\ub798 \uacc4\ud68d\ub300\ub85c \ud504\ub85c\ub77c \ub9ac\uc870\ud2b8\ub294 10\uac1c \ub2e8\uc9c0\uac00 8\uac1c \uad6c\uc5ed\uc744 \uc774\ub8e8\uc5b4 2\ub9cc \uba85\uc758 \ud734\uc591\uac1d\uc5d0\uac8c \ubc29\uc744 \uc81c\uacf5\ud560 \uc218 \uc788\uc5c8\ub2e4. \uc644\uc131\ub418\uba74 \uc2dd\ub2f9, \uc601\ud654\uad00, \uc218\uc601\uc7a5, \uccb4\uc721\uad00, \ubb34\ub3c4\ud68c\uc7a5 \ub4f1 \uc624\ub77d\ud3b8\uc758\uc2dc\uc124\uc744 \uac16\ucd94\uace0 \ucca0\ub3c4\uc5ed\uacfc \uc720\ub78c\uc120 \ubd80\ub450\ub97c \ud1b5\ud574 \uc774\uc6a9\ud560 \uc218 \uc788\uc5c8\ub2e4. \uadf8\ub7ec\ub098 2\ucc28 \uc138\uacc4\ub300\uc804\uc774 \ud130\uc9c0\uba74\uc11c \uac74\uc124\uc774 \uc911\ub2e8\ub418\uc5c8\uace0, \uc804\uc7c1 \ub3d9\uc548 \uac74\ubb3c\uc740 \ud53c\ub09c\ubbfc\uc744 \uc218\uc6a9\ud558\ub294 \ub370 \uc4f0\uc600\uc73c\uba70, \ub098\uc911\uc5d0\ub294 \uc721\uad70 \ubcd1\uc6d0\uc774 \ub418\uc5c8\ub2e4. \uc804\uc7c1 \uc774\ud6c4\uc5d0\ub294 \uc18c\ube44\uc5d0\ud2b8 \uc5f0\ubc29\uc774 \ud55c\ub3d9\uc548 \ucc28\uc9c0\ud588\uace0, \uadf8 \ub4a4\uc5d0\ub294 \ubc30\uc120\ubd80\ud130 \ubc30\uad00\uae4c\uc9c0 \uc4f8\ub9cc\ud55c \uc790\uc7ac\ub97c \ubaa8\ub450 \ubc97\uaca8 \ub0c8\ub2e4. \ub3d9\ub3c5 \uc5ed\uc0ac\ubc15\ubb3c\uad00\uc744 \uc81c\uc678\ud55c \ub2e8\uc9c0 \ub300\ubd80\ubd84\uc774 \ud5c8\ubb3c\uc5b4\uc84c\ub2e4.",
    "icon": "https://eyefyre.github.io/civvapi/images/wonder_icons/\ud504\ub85c\ub77c.png",
    "background_image": "https://eyefyre.github.io/civvapi/images/wonder_backgrounds/\ud504\ub85c\ub77c.png",
    "quote": "'(\uc790\uc720\uc758) \uc0c1\uc2e4\uc740 \uc778\uac04\uc774 \uac00\uc7a5 \uc18c\uc911\ud788 \uc5ec\uae30\ub294 \uac00\uce58\uad00\uc774 \ubab0\ub77d\ud588\uc74c\uc744 \ub73b\ud55c\ub2e4. \uc774\ud6c4\ub85c\ub294 \uace0\uc6a9\uc790\uc640 \ud53c\uace0\uc6a9\uc790\uc758 \uc5c4\uaca9\ud55c \uad00\uacc4\uc5d0 \uc5bd\ub9e4\uc5ec \uc0ac\uc18c\ud55c \uc990\uac70\uc6c0\ub9cc\uc744 \ub204\ub9b4 \ubfd0\uc774\ub2e4.' - A.N. \ud654\uc774\ud2b8\ud5e4\ub4dc",
    "tech_prereq": {
        "name": "Flight",
        "url": "https://eyefyre.github.io/civvapi/v1/kr/tech/flight.json"
    },
    "yields": {
        "gold": 0,
        "production": 0,
        "science": 0,
        "culture": 0,
        "food": 0,
        "faith": 0,
        "happiness": 2
    }
}