{
    "id": 40,
    "name": "\uc790\uc720\uc758 \uc5ec\uc2e0\uc0c1",
    "production_cost": 1060,
    "game_info": "\ud3c9\ub4f1\uc774 \ud544\uc694\ud569\ub2c8\ub2e4. \ubaa8\ub4e0 \ub3c4\uc2dc\uc758 \uc804\ubb38\uac00\uc5d0 \uc758\ud55c \uc0dd\uc0b0\uc774 1 \uc99d\uac00\ud558\uace0 \uc0ac\ud68c \uc815\ucc45 1\uac1c\ub97c \uc989\uc2dc \ucc44\ud0dd\ud560 \uc218 \uc788\uc2b5\ub2c8\ub2e4.",
    "strategy": null,
    "historical_info": "\uc790\uc720\uc758 \uc5ec\uc2e0\uc0c1\uc740 \uc138\uacc4 \ucd5c\ub300\uc758 \uc785\uc0c1 \uc911 \ud558\ub098\ub2e4. \ubc1b\uce68\ub300 \ubc14\ub2e5\uc73c\ub85c\ubd80\ud130 \uc7b0 \ub192\uc774\uac00 90m\uac00 \ub118\ub294 \uc790\uc720\uc758 \uc5ec\uc2e0\uc0c1\uc740, \ucca0\uc81c \uace8\uaca9\uc5d0 \uad6c\ub9ac\ud310\uc744 \ub367\ub300 \uc81c\uc791\ub418\uc5c8\uc73c\uba70 \uadf8 \ubb34\uac8c\ub294 250\ud1a4\uc774 \ub118\ub294\ub2e4. \ud504\ub791\uc2a4 \uc870\uac01\uac00 \ud504\ub808\ub4dc\ub9ad \ubc14\ub974\ud1a8\ub514\uac00 \uc124\uacc4\ud55c \uc5ec\uc2e0\uc0c1\uc740 \ud683\ubd88\uc744 \ub192\uc774 \ub4e4\uace0 \uc788\uc73c\uba70 \ubc1c\uce58\uc5d0\ub294 \uc555\uc81c\ub97c \ub098\ud0c0\ub0b4\ub294 \uc1e0\uc0ac\uc2ac\uc774 \ub04a\uc5b4\uc9c4 \ucc44 \ub193\uc5ec\uc788\ub2e4. 1886\ub144 \ud504\ub791\uc2a4 \uc815\ubd80\uac00 \ubbf8\uad6d \ub3c5\ub9bd 100\uc8fc\ub144\uc744 \uae30\ub150\ud558\uae30 \uc704\ud574 \ubbf8\uad6d\uc5d0 \uc790\uc720\uc758 \uc5ec\uc2e0\uc0c1\uc744 \uc120\ubb3c\ud588\ub2e4. \uc790\uc720\uc758 \uc5ec\uc2e0\uc0c1 \uc790\uccb4\uc640 \ub9ac\ubc84\ud2f0 \uc12c \uadf8\ub9ac\uace0 \uadfc\ucc98\uc758 \uc5d8\ub9ac\uc2a4 \uc12c\uc740 1924\ub144\uc5d0 \uad6d\uac00 \uae30\ub150\ubb3c\ub85c \uc81c\uc815\ub418\uc5c8\ub2e4.100\ub144\uc774 \ub118\ub294 \uc138\uc6d4 \ub3d9\uc548 \uc790\uc720\uc758 \uc5ec\uc2e0\uc0c1\uc740 \ub274\uc695 \ud56d\uc758 \uc785\uad6c\uc5d0 \uc11c \uc788\uc5c8\ub2e4. \ubbf8\uad6d\uc5d0 \uc785\uc131\ud558\ub294 \uc774\ubbfc\uc790\ub4e4\uc774 \ucc98\uc74c \ubcf4\uac8c \ub418\ub294 \uad11\uacbd\uc774\uae30\ub3c4 \ud55c \uc790\uc720\uc758 \uc5ec\uc2e0\uc0c1\uc740 \ubbf8\uad6d\uc758 \uac74\uad6d \uc774\ub150\uc778 \uc790\uc720\ub97c \uc0c1\uc9d5\ud55c\ub2e4.",
    "icon": "https://eyefyre.github.io/civvapi/images/wonder_icons/statue_of_liberty.png",
    "background_image": "https://eyefyre.github.io/civvapi/images/wonder_backgrounds/statue_of_liberty.png",
    "quote": "\"\uace0\ub2e8\ud55c \uc790\uc5ec, \uac00\ub09c\ud55c \uc790\uc5ec, \uc790\uc720\ub85c\uc774 \uc228\uc26c\uace0\uc790 \ud558\ub294 \uad70\uc911\uc774\uc5ec, \ub0b4\uac8c\ub85c \uc624\ub77c.\ub108\ud76c \ub4e4\ub053\ub294 \ud574\ubcc0\uc758 \ucd08\ub77c\ud55c \uc790\uc5ec,\uac08 \uacf3\uc774 \uc5c6\ub294 \uc790\uc5ec, \ud3ed\ud48d\uc5d0 \ud729\uc4f8\ub9b0 \uc790\uc5ec, \ub0b4\uac8c\ub85c \uc624\ub77c.\ub0b4\uac00 \ud669\uae08 \ubb38 \uc606\uc5d0 \ub4f1\ubd88\uc744 \ub192\uc774 \uccd0\ub4e4\ub9ac\ub77c!\" - \uc5e0\ub9c8 \ub77c\uc790\ub8e8\uc2a4",
    "tech_prereq": {
        "name": "Replaceable Parts",
        "url": "https://eyefyre.github.io/civvapi/v1/kr/tech/replaceable_parts.json"
    },
    "yields": {
        "gold": 0,
        "production": 0,
        "science": 0,
        "culture": 1,
        "food": 0,
        "faith": 0,
        "happiness": 0
    }
}