{
    "id": 10,
    "name": "Ko\u0142o|Ko\u0142u|Ko\u0142u|Ko\u0142o",
    "icon": "https://eyefyre.github.io/civvapi/images/tech_icons/the_wheel.png",
    "era": "Staro\u017cytno\u015b\u0107|Staro\u017cytno\u015bci|Staro\u017cytno\u015bci|Staro\u017cytno\u015b\u0107",
    "cost": 55,
    "civilopedia_entry": "Ko\u0142o to okr\u0105g\u0142y przedmiot z dziur\u0105 lub osi\u0105 po \u015brodku. Samo praktycznie do niczego si\u0119 nie nadaje, ale jako cz\u0119\u015b\u0107 systemu transportowego z\u0142o\u017conego z dr\u00f3g i zwierz\u0105t poci\u0105gowych ma olbrzymi\u0105 warto\u015b\u0107 dla cywilizacji ludzkiej. Najwcze\u015bniejszy rysunek pojazdu ko\u0142owego zosta\u0142 znaleziony w staro\u017cytnym Sumerze oko\u0142o 3500 r. p.n.e. Pierwsze ko\u0142a by\u0142y w ca\u0142o\u015bci drewniane; szprychy pojawi\u0142y si\u0119 oko\u0142o 2000 r. p.n.e. w Azji Mniejszej, gdzie montowano je w konnych rydwanach. P\u00f3\u017aniejsze modyfikacje to \u017celazne piasty obracaj\u0105ce si\u0119 na nasmarowanych osiach oraz resory lub inne elementy poch\u0142aniaj\u0105ce wstrz\u0105sy.W przeciwie\u0144stwie do popularnego mitu, w Nowym \u015awiecie ko\u0142o by\u0142o znane ju\u017c przed przybyciem Hiszpan\u00f3w. Jednak w Ameryce P\u00f3\u0142nocnej, \u015arodkowej i Po\u0142udniowej brakowa\u0142o zwierz\u0105t poci\u0105gowych, wi\u0119c w\u0142a\u015bciwie wszystko transportowali ludzie. Cz\u0142owiek jednak nie mo\u017ce ci\u0105gn\u0105\u0107 przedmiot\u00f3w na du\u017ce odleg\u0142o\u015bci: du\u017co lepiej radzi sobie, nosz\u0105c ci\u0119\u017cary na barkach \u2013 na przyk\u0142ad w plecaku \u2013 wi\u0119c w tamtym rejonie nigdy nie powsta\u0142y wozy. Kiedy pojawi\u0142y si\u0119 konie i inne zwierz\u0119ta poci\u0105gowe, rdzenni Amerykanie zacz\u0119li ochoczo korzysta\u0107 z pojazd\u00f3w ko\u0142owych.",
    "quote": "\u201eM\u0105dro\u015b\u0107 i cnota s\u0105 jak dwa ko\u0142a wozu.\u201d \u2013 przys\u0142owie japo\u0144skie",
    "tech_prereqs": [
        {
            "name": "Hodowla zwierz\u0105t|Hodowli zwierz\u0105t|Hodowli zwierz\u0105t|Hodowl\u0119 zwierz\u0105t",
            "url": "https://eyefyre.github.io/civvapi/v1/pl/tech/animal_husbandry.json"
        },
        {
            "name": "\u0141ucznictwo|\u0141ucznictwa|\u0141ucznictwu|\u0141ucznictwo",
            "url": "https://eyefyre.github.io/civvapi/v1/pl/tech/archery.json"
        }
    ],
    "tech_unlocks": [
        {
            "name": "Jazda konna|Jazdy konnej|Je\u017adzie konnej|Jazd\u0119 konn\u0105",
            "url": "https://eyefyre.github.io/civvapi/v1/pl/tech/horseback_riding.json"
        },
        {
            "name": "Matematyka|Matematyki|Matematyce|Matematyk\u0119",
            "url": "https://eyefyre.github.io/civvapi/v1/pl/tech/mathematics.json"
        },
        {
            "name": "Budownictwo|Budownictwa|Budownictwu|Budownictwo",
            "url": "https://eyefyre.github.io/civvapi/v1/pl/tech/construction.json"
        }
    ],
    "unit_unlocks": [
        {
            "name": "Strzelcy rydwanowi|Strzelc\u00f3w rydwanowych|Strzelcom rydwanowym|Strzelc\u00f3w rydwanowych",
            "url": "https://eyefyre.github.io/civvapi/v1/pl/units/chariot_archer.json"
        },
        {
            "name": "Rydwany bojowe|Rydwan\u00f3w bojowych|Rydwanom bojowym|Rydwan\u00f3w bojowych",
            "url": "https://eyefyre.github.io/civvapi/v1/pl/units/war_chariot.json"
        },
        {
            "name": "S\u0142onie bojowe|S\u0142oni bojowych|S\u0142oniom bojowym|S\u0142onie bojowe",
            "url": "https://eyefyre.github.io/civvapi/v1/pl/units/war_elephant.json"
        },
        {
            "name": "\u0141ucznicy konni|\u0141ucznik\u00f3w konnych|\u0141ucznikom konnym|\u0141ucznik\u00f3w konnych",
            "url": "https://eyefyre.github.io/civvapi/v1/pl/units/horse_archer.json"
        }
    ],
    "building_unlocks": [
        {
            "name": "P\u0142ywaj\u0105ce ogrody|P\u0142ywaj\u0105cych ogrod\u00f3w|P\u0142ywaj\u0105cym ogrodom|P\u0142ywaj\u0105ce ogrody",
            "url": "https://eyefyre.github.io/civvapi/v1/pl/buildings/floating_gardens.json"
        },
        {
            "name": "M\u0142yn wodny|M\u0142ynu wodnego|M\u0142ynowi wodnemu|M\u0142yn wodny|M\u0142yny wodne|M\u0142yn\u00f3w wodnych|M\u0142ynom wodnym|M\u0142yny wodne",
            "url": "https://eyefyre.github.io/civvapi/v1/pl/buildings/water_mill.json"
        }
    ]
}