{
    "id": 41,
    "name": "Cultura de los medios",
    "game_info": " +34% al Turismo generado por ciudades con una Torre de difusi\u00f3n.",
    "historical_info": "La cultura de los medios se refiere a la sociedad capitalista occidental actual que emergi\u00f3 a finales del siglo XX, caracterizada por el consumismo fomentado por los medios de comunicaci\u00f3n de masas. Los cr\u00edticos consideran que la cultura de los medios, con su \u00e9nfasis en la publicidad y las relaciones p\u00fablicas, es un sistema centrado en la manipulaci\u00f3n de masas, sobre todo al respecto de la representaci\u00f3n y reproducci\u00f3n de ideolog\u00edas dominantes. Eruditos de la talla de Theodor Adorno y Hannah Arendt han escrito ampliamente acerca del impacto de la cultura de los medios en la democracia y el capitalismo.",
    "icon": "https://eyefyre.github.io/civvapi/images/policy_icons/cultura_de_los_medios.png",
    "required_policies": [],
    "tenet_level": 3,
    "branch": {
        "name": "Igualdad",
        "game_info": "La Igualdad va mejor para los imperios peque\u00f1os y centrados. En concreto, concede bonificaciones para los Grandes personajes y los especialistas.Tras adoptar la Igualdad, la velocidad con la que nacen los Grandes personajes aumenta en un 25%.Adoptar todas las pol\u00edticas del \u00e1rbol de la Igualdad aumentar\u00e1 el rendimiento b\u00e1sico de las mejoras de casillas grandes en un 100%, y la duraci\u00f3n de las Edades de Oro se prolongar\u00e1 un 50%.Puedes adquirir Grandes artistas con Fe .[COLOR_WARNING_TEXT]Esta rama no puede estar activa al mismo tiempo que la Autocracia o el Orden.",
        "prereq_era": "Era Industrial",
        "historical_info": null
    }
}