{
    "id": 17,
    "name": "Stra\u017c|Stra\u017cy|Stra\u017cy|Stra\u017c",
    "game_info": "+1 do zasi\u0119gu widzenia.",
    "prereq_promotions": [
        {
            "name": "Szturm I|Szturmu I|Szturmowi I|Szturm I",
            "url": "https://eyefyre.github.io/civvapi/v1/pl/promotions/shock_i.json"
        },
        {
            "name": "Wyszkolenie I|Wyszkolenia I|Wyszkoleniu I|Wyszkolenie I",
            "url": "https://eyefyre.github.io/civvapi/v1/pl/promotions/drill_i.json"
        },
        {
            "name": "Celowanie I|Celowania I|Celowaniu I|Celowanie I",
            "url": "https://eyefyre.github.io/civvapi/v1/pl/promotions/targeting_i.json"
        },
        {
            "name": "Bombardowanie I|Bombardowania I|Bombardowaniu I|Bombardowanie I",
            "url": "https://eyefyre.github.io/civvapi/v1/pl/promotions/bombardment_i.json"
        },
        {
            "name": "Morski grabie\u017cca I",
            "url": "https://eyefyre.github.io/civvapi/v1/pl/promotions/coastal_raider_i.json"
        },
        {
            "name": "Oddzia\u0142y aborda\u017cowe I",
            "url": "https://eyefyre.github.io/civvapi/v1/pl/promotions/boarding_party_i.json"
        },
        {
            "name": "Wataha I",
            "url": "https://eyefyre.github.io/civvapi/v1/pl/promotions/wolfpack_i.json"
        },
        {
            "name": "Pok\u0142ad lotniczy I",
            "url": "https://eyefyre.github.io/civvapi/v1/pl/promotions/flight_deck_i.json"
        },
        {
            "name": "Opancerzenie I",
            "url": "https://eyefyre.github.io/civvapi/v1/pl/promotions/armor_plating_i.json"
        }
    ],
    "icon": "https://eyefyre.github.io/civvapi/images/promotion_icons/stra\u017c|stra\u017cy|stra\u017cy|stra\u017c_s.png"
}