{
    "id": 22,
    "name": "\uc2e0\ud559",
    "icon": "https://eyefyre.github.io/civvapi/images/tech_icons/theology.png",
    "era": "\uc911\uc138 \uc2dc\ub300",
    "cost": 275,
    "civilopedia_entry": "\uc2e0\ud559\uc740 \uc885\uad50\ub97c \uc5f0\uad6c\ud558\ub294 \ud559\ubb38\uc774\ub2e4. \uc2e0\ud559\uc790\ub294 \uc885\uad50 \uc804\ud1b5\uacfc \uc2e0\uc559\uc744 \uc5f0\uad6c\ud55c\ub2e4. \uc2e0\ud559\uc740 \uc801\uc5b4\ub3c4, \uc2e0\ud654\uc640 \uc9c0\ucf1c\uc57c \ud560 \uc885\uad50 \uc804\ud1b5\uc774 \ud48d\ubd80\ud55c \uace0\uc804\uc2dc\ub300 \uadf8\ub9ac\uc2a4\uc778\uae4c\uc9c0 \uac70\uc2ac\ub7ec \uc62c\ub77c\uac04\ub2e4. \uae30\uc6d0\ud6c4 1-2\uc138\uae30\uc5d0 \uc720\ub300\uad50\uc758 \uc885\uad50 \uc5f0\uad6c\uac00 \uaf43\uc744 \ud53c\uc6e0\ub2e4. \uc720\ub300\uad50 \uad6c\uc804 \uc804\uc2b9\uc744 \ub78d\ube44\uc5b4\ub85c \uae30\ub85d\ud55c \uc608\ub8e8\uc0b4\ub818 \ud0c8\ubb34\ub4dc\uac00 \uae30\uc6d0 \ud6c4 200\ub144\uacbd \ucd9c\uac04\ub418\uc5c8\uace0, \uadf8 \ud6c4 2\uc138\uae30\uac04 \ub0b4\uc6a9\uc5d0 \uc0b4\uc774 \ubd99\uace0 \ud655\uc7a5\ub418\uc5c8\ub2e4.\uc2e0\ud559\uc758 \uc911\uc694\ud558\uba70 \uc138\uacc4\uc0ac\uc5d0 \uc9c0\ub300\ud55c \uc601\ud5a5\uc744 \ub07c\ucce4\ub2e4. \uc140 \uc218 \uc5c6\ub294 \uc0ac\ub78c\ub4e4\uc774 \uc885\uad50 \ubd84\uc7c1 \ub54c\ubb38\uc5d0 \uc8fd\uc5b4\uac14\uace0, \ubc14\ub85c \uc9c0\uae08 \uc774 \uc21c\uac04\uc5d0\ub3c4 \uc8fd\uc5b4\uac00\uace0 \uc788\ub2e4. \ub85c\ub9c8\uc778\uc740 \ub85c\ub9c8 \uc2e0\uc758 \uc874\uc7ac\ub97c \ubd80\uc778\ud55c \uae09\uc9c4\uc801 \uc2e0\ud559 \ub54c\ubb38\uc5d0 \uae30\ub3c5\uad50\uc778\uc744 \ud559\uc0b4\ud588\ub2e4. \uae30\ub3c5\uad50\uc778\uc740 \uc885\uad50 \ubd84\uc7c1\uc73c\ub85c \uc720\ub300\uc778\uacfc \uc774\uc2ac\ub78c\uad50\uc778, \uae30\ub3c5\uad50\uc778\uc744 \ud559\uc0b4\ud588\ub2e4. \uc2e0\ud559\uc790\uc774\uc790 \uae30\ub3c5\uad50 \ud601\uba85\uac00\uc778 \ub9c8\ub974\ud2f4 \ub8e8\ud130\ub294 \u201895\uac1c\uc870 \ubc18\ubc15\ubb38\u2019\uacfc \uc131 \ubca0\ub4dc\ub85c \ubc14\uc2e4\ub9ac\uce74 \uac74\ub9bd\uc744 \uc704\ud55c \uba74\uc8c4\ubd80 \ud310\ub9e4\ub85c, \uc720\ub7fd\uc5d0\uc11c \uc218\ubc31 \ub144\uc5d0 \uac78\uce5c \uc794\uc778\ud55c \uc885\uad50 \uc804\uc7c1\uc744 \ucd09\ubc1c\ud588\ub2e4. \uc885\uad50 \uc804\uc7c1\uc774 \ub05d\uc774 \ub0a0 \uc218\ub9cc \uc788\ub2e4\uba74, \uc2e0\ud559\uc774\uc57c\ub9d0\ub85c \uae09\uc9c4\uc801 \uc774\uc2ac\ub78c \uad50\uc778\uacfc \uc11c\uc591 \uc138\uacc4\uc758 \uc885\uad50 \uc804\uc7c1\uc744 \ud574\uacb0\ud558\ub294 \ub370 \uacb0\uc815\uc801\uc778 \uc5ed\ud560\uc744 \ud560 \uac83\uc774\ub2e4.",
    "quote": "\"\uc778\uac04\uc758 \uad6c\uc6d0\uc5d0\ub294 \uc138 \uac00\uc9c0\uac00 \ud544\uc694\ud558\ub2e4. \ubbff\uc744 \uac83\uc744 \uc544\ub294 \uac83, \ucd94\uad6c\ud560 \uac83\uc744 \uc544\ub294 \uac83, \ud574\uc57c \ud560 \uac83\uc744 \uc544\ub294 \uac83\uc774\ub2e4.\" - \uc131 \ud1a0\ub9c8\uc2a4 \uc544\ud034\ub098\uc2a4",
    "tech_prereqs": [
        {
            "name": "\ucca0\ud559",
            "url": "https://eyefyre.github.io/civvapi/v1/kr/tech/philosophy.json"
        },
        {
            "name": "\ub4dc\ub77c\ub9c8\uc640 \uc2dc",
            "url": "https://eyefyre.github.io/civvapi/v1/kr/tech/drama_and_poetry.json"
        }
    ],
    "tech_unlocks": [
        {
            "name": "\ub098\uce68\ubc18",
            "url": "https://eyefyre.github.io/civvapi/v1/kr/tech/compass.json"
        },
        {
            "name": "\uad50\uc721\ud559",
            "url": "https://eyefyre.github.io/civvapi/v1/kr/tech/education.json"
        }
    ],
    "unit_unlocks": [],
    "building_unlocks": [
        {
            "name": "\uc815\uc6d0",
            "url": "https://eyefyre.github.io/civvapi/v1/kr/buildings/garden.json"
        },
        {
            "name": "\uc131 \uc18c\ud53c\uc544 \ub300\uc131\ub2f9",
            "url": "https://eyefyre.github.io/civvapi/v1/kr/buildings/hagia_sophia.json"
        },
        {
            "name": "\uc820\ub124 \ubaa8\uc2a4\ud06c",
            "url": "https://eyefyre.github.io/civvapi/v1/kr/buildings/great_mosque_of_djenne.json"
        },
        {
            "name": "\ub300\uc0ac\uc6d0",
            "url": "https://eyefyre.github.io/civvapi/v1/kr/buildings/grand_temple.json"
        },
        {
            "name": "\ucc2c\ub514",
            "url": "https://eyefyre.github.io/civvapi/v1/kr/buildings/candi.json"
        },
        {
            "name": "\ubcf4\ub85c\ubd80\ub450\ub974 \uc0ac\uc6d0",
            "url": "https://eyefyre.github.io/civvapi/v1/kr/buildings/borobudur.json"
        }
    ]
}