{
    "id": 83,
    "name": "\uc870\uc57d \uae30\uad6c",
    "game_info": "\uad50\uc5ed\ub85c\uac00 \uc5f0\uacb0\ub41c \ub3c4\uc2dc \uad6d\uac00\uc758 \uc6b0\ud638\ub3c4\uac00 \ud134\ub2f9 4(\uc77c\ubc18\uc801\uc778 \uc18d\ub3c4\ub85c) \uc99d\uac00\ud569\ub2c8\ub2e4.",
    "historical_info": "\uc870\uc57d \uae30\uad6c\ub294 \ud68c\uc6d0\uad6d\uc758 \uc548\ubcf4\ub97c \ubcf4\uc7a5\ud558\ub294 \uad6d\uc81c \uad70\uc0ac \uc870\uc57d\uc774\ub2e4. \ub530\ub77c\uc11c \uc870\uc57d \uae30\uad6c\ub294 \uc77c\ubc18\uc801\uc778 \uad70\uc0ac \ud65c\ub3d9\uc740 \uc9c0\ud718\ud568\uc740 \ubb3c\ub860 \uc5f0\ud569 \uc0ac\ub839\ubd80, \uc5f0\uad6c \uc2dc\uc124 \ubc0f \uad70\uc218 \uc2dc\uc124\uc744 \uc6b4\uc6a9\ud55c\ub2e4. 1949\ub144\uc5d0 \uc2dc\uc791\ub41c \ubd81\ub300\uc11c\uc591\uc870\uc57d\uae30\uad6c(NATO)\uac00 \uac00\uc7a5 \uc720\uba85\ud55c \uc608\uc774\uba70, \ub0a8\uc544\uba54\ub9ac\uce74\ub098 \uc544\ud504\ub9ac\uce74 \ub300\ub959\uc5d0\ub3c4 \ube44\uc2b7\ud55c \uc870\uc57d \uae30\uad6c\uac00 \uc874\uc7ac\ud55c\ub2e4. \uacfc\uac70\uc5d0\ub3c4 \ubc29\uc5b4 \uc870\uc57d\uc774\ub098 \uad70\uc0ac \ub3d9\ub9f9\uc740 \ud754\ud588\uc9c0\ub9cc, \ud604\ub300\ud654\ub41c \uc870\uc57d \uae30\uad6c\ub294 \ud68c\uc6d0\uad6d \uc0ac\uc774\uc758 \ud611\ub825 \uc218\uc900\uc744 \uc0c8\ub85c\uc6b4 \ub2e8\uacc4\ub85c \ub04c\uc5b4\uc62c\ub838\ub2e4.",
    "icon": "https://eyefyre.github.io/civvapi/images/policy_icons/\uc870\uc57d_\uae30\uad6c.png",
    "required_policies": [],
    "tenet_level": 3,
    "branch": {
        "name": "\ud3c9\ub4f1",
        "game_info": "\ud3c9\ub4f1\uc740 \uaddc\ubaa8\uac00 \uc791\uace0 \ud55c \uac00\uc9c0\uc5d0 \uc9d1\uc911\ud558\ub294 \ubb38\uba85\uc5d0 \uc801\ud569\ud569\ub2c8\ub2e4. \uc704\uc778\uacfc \uc804\ubb38\uac00\uc5d0 \ubcf4\ub108\uc2a4\ub97c \uc81c\uacf5\ud558\ub294 \ud2b9\uc9d5\uc774 \uc788\uc2b5\ub2c8\ub2e4.\ud3c9\ub4f1\uc744 \ucc44\ud0dd\ud558\uba74 \uc704\uc778 \ucd9c\ud604\uc728\uc774 25%\ub9cc\ud07c \uc99d\uac00\ud569\ub2c8\ub2e4.\ud3c9\ub4f1 \uacc4\uc5f4\uc758 \uc815\ucc45\uc744 \ubaa8\ub450 \ucc44\ud0dd\ud558\uba74 \uc704\uc778\uc73c\ub85c \uac74\uc124\ud558\ub294 \uc2dc\uc124\uc758 \uae30\ubcf8 \uc0dd\uc0b0\ub7c9\uc774 100%\ub9cc\ud07c \uc99d\uac00\ud558\uba70 \ud669\uae08\uae30\uac00 50%\ub9cc\ud07c \ub354 \uc9c0\uc18d\ub429\ub2c8\ub2e4. \uc2e0\uc559\uc73c\ub85c \uc704\ub300\ud55c \uc608\uc220\uac00\ub97c \uad6c\uc785\ud560 \uc218 \uc788\uc2b5\ub2c8\ub2e4.[COLOR_WARNING_TEXT]\ud3c9\ub4f1\uc740 \uc804\uc81c\uc815\uce58\ub098 \uc9c8\uc11c\uc640 \ub3d9\uc2dc\uc5d0 \ud65c\uc131\ud654\ud560 \uc218 \uc5c6\uc2b5\ub2c8\ub2e4.",
        "prereq_era": "\uc0b0\uc5c5 \uc2dc\ub300",
        "historical_info": null
    }
}