{
    "id": 10,
    "name": "Grand Mesa|Grand Mesy|Grand Mesie|Grand Mes\u0119",
    "historical_info": "Grand Mesa jest wielk\u0105 formacj\u0105 geologiczn\u0105 znajduj\u0105c\u0105 si\u0119 w Kolorado, w Stanach Zjednoczonych Ameryki P\u00f3\u0142nocnej. Wznosi si\u0119 ona 1,5 kilometra nad otaczaj\u0105cym terenem, zajmuje obszar 1300 kilometr\u00f3w kwadratowych i jest najwi\u0119kszym p\u0142askowy\u017cem na \u015bwiecie. Grand Mesa ma na szczycie warstw\u0119 wulkanicznego bazaltu, kt\u00f3ry nie jest podatny na erozj\u0119. Ca\u0142o\u015b\u0107 nie tyle unios\u0142a si\u0119, ile pozosta\u0142a na niezmienionym poziomie, podczas gdy otaczaj\u0105cy teren uleg\u0142 erozji pod wp\u0142ywem wody rzek Kolorado i Gunnison.",
    "icon": "https://eyefyre.github.io/civvapi/images/feature_icons/grand_mesa|grand_mesy|grand_mesie|grand_mes\u0119.png",
    "movement_cost": -1,
    "combat_modifier": 0,
    "yields": {
        "gold": 3,
        "production": 2,
        "science": 0,
        "culture": 0,
        "food": 0,
        "faith": 0,
        "happiness": 0
    },
    "resources": []
}