{
    "id": 1,
    "name": "Mosqu\u00e9e|Mosqu\u00e9es",
    "game_info": null,
    "strategy": "Ne peut \u00eatre construite que dans les villes converties \u00e0 une religion croyant au caract\u00e8re sacr\u00e9 des mosqu\u00e9es. Ce b\u00e2timent doit \u00eatre achet\u00e9 avec de la foi.",
    "historical_info": "La mosqu\u00e9e est le lieu de culte traditionnel des adeptes de l'Islam. La plus grande mosqu\u00e9e au monde, Masjid al-Haram, fut construite dans la ville de La Mecque, en Arabie saoudite, aux alentours de l'an 638. Aussi appel\u00e9e la Grande Mosqu\u00e9e, Masjid al-Haram englobe le lieu saint de la Kaaba, le plus sacr\u00e9 de tous les sites de la religion islamique.",
    "cost": {
        "production": -1,
        "faith": 200
    },
    "gold_maintenance": 0,
    "icon": "https://eyefyre.github.io/civvapi/images/building_icons/mosqu\u00e9e|mosqu\u00e9es.png",
    "prereq_tech": null,
    "yields": {
        "gold": 0,
        "production": 0,
        "science": 0,
        "culture": 2,
        "food": 0,
        "faith": 3,
        "happiness": 1
    }
}