{
    "id": 18,
    "name": "\u5bf6\u77f3",
    "game_info": null,
    "historical_info": "\u5bf6\u77f3\u662f\u4e00\u7a2e\u7f8e\u9e97\u4f46\u7f55\u898b\u7684\u7926\u7269\u3002\u4e00\u65e6\u5207\u5272\u548c\u6253\u78e8\u4e4b\u5f8c\uff0c\u5bf6\u77f3\u6703\u64c1\u6709\u9bae\u8c54\u7684\u8272\u5f69\u6216\u6df7\u5408\u6975\u7aef\u70ab\u9e97\u7684\u5149\u8292\u3002\u5bf6\u77f3\u4e3b\u8981\u5206\u70ba\u5169\u985e\uff1a\u5bf6\u77f3\uff0c\u50cf\u947d\u77f3\u3001\u7d05\u5bf6\u77f3\u3001\u7da0\u5bf6\u77f3\uff1b\u4ee5\u53ca\u534a\u5bf6\u77f3\uff0c\u6bd4\u5982\u7d2b\u6c34\u6676\uff0c\u7da0\u677e\u77f3\u7b49\u7b49\u3002\u5bf6\u77f3\u5728\u6b77\u53f2\u4e0a\u4e00\u76f4\u90fd\u88ab\u9ad8\u5ea6\u91cd\u8996\u3002\u800c\u6709\u9322\u6709\u52e2\u7684\u4eba\u58eb\u901a\u5e38\u628a\u5b83\u5011\u7528\u4f86\u88dd\u98fe\u9996\u98fe\u4ee5\u53ca\u5c45\u5bb6\u7528\u54c1\u3002",
    "icon": "https://eyefyre.github.io/civvapi/images/resource_icons/\u5bf6\u77f3.png",
    "prereq_tech": null,
    "yields": {
        "gold": 3,
        "production": 0,
        "science": 0,
        "culture": 0,
        "food": 0,
        "faith": 0,
        "happiness": 0
    },
    "improved_by": [
        {
            "name": "\u7926\u5834",
            "url": "https://eyefyre.github.io/civvapi/v1/zh/improvements/mine.json"
        }
    ],
    "terrains_found_on": [
        {
            "name": "\u53e2\u6797",
            "url": "https://eyefyre.github.io/civvapi/v1/zh/features/\u53e2\u6797.json"
        },
        {
            "name": "\u8349\u539f",
            "url": "https://eyefyre.github.io/civvapi/v1/zh/terrains/\u8349\u539f.json"
        },
        {
            "name": "\u5e73\u539f",
            "url": "https://eyefyre.github.io/civvapi/v1/zh/terrains/\u5e73\u539f.json"
        },
        {
            "name": "\u6c99\u6f20",
            "url": "https://eyefyre.github.io/civvapi/v1/zh/terrains/\u6c99\u6f20.json"
        },
        {
            "name": "\u51cd\u571f",
            "url": "https://eyefyre.github.io/civvapi/v1/zh/terrains/\u51cd\u571f.json"
        },
        {
            "name": "\u4e18\u9675",
            "url": "https://eyefyre.github.io/civvapi/v1/zh/terrains/\u4e18\u9675.json"
        }
    ]
}