{
    "id": 17,
    "name": "\uce90\ub7ec\ubca8",
    "icon": "https://eyefyre.github.io/civvapi/images/unit_icons/caravel.png",
    "game_info": "\ub974\ub124\uc0c1\uc2a4 \uc2dc\ub300 \uc720\ub2db\uc73c\ub85c, \ube60\ub974\uace0 \uc2dc\uc57c\uac00 \ub113\uc73c\uba70 \ub300\uc591\uc744 \uac74\ub110 \uc218 \uc788\uc5b4 \ud0d0\ud5d8\uc5d0 \uc801\ud569\ud569\ub2c8\ub2e4. \ud574\uc0c1 \uadfc\uc811 \uc720\ub2db\uc785\ub2c8\ub2e4.",
    "historical_info": "\uce90\ub7ec\ubca8\uc740 15\uc138\uae30 \uc0ac\ub78c\ub4e4\uc774 \uba3c\ubc14\ub2e4\ub97c \ud56d\ud574\ud560 \ub54c \uc4f4 \ubc30\ub2e4. \ud3ec\ub974\ud22c\uac08\uc758 \ud56d\ud574\uc655 \ud5e8\ub9ac\uc758 \uba85\ub839\uc73c\ub85c \ucc98\uc74c \ub9cc\ub4e4\uc5b4\uc9c4 \uce90\ub7ec\ubca8\uc740 \uc131\ub2a5\uc774 \ub6f0\uc5b4\ub0ac\uc73c\ubbc0\ub85c \uae08\uc138 \uc8fc\ubcc0 \uad6d\uac00\ub85c \ud37c\uc84c\ub2e4. \ubcf4\ud1b5 \uc804\uc7a5\uc774 18m\uc5d0\uc11c 27m\uc5d0 \uc774\ub974\uace0 \uc0bc\uac01 \ub3db\ub300\ub97c \ub450 \uac1c\ub098 \uc138 \uac1c \ub2e8 \uce90\ub7ec\ubca8\uc740 \uac00\ubccd\uace0 \ud758\uc218\uc120\uc774 \uc595\uc544 \ud070 \uc120\ubc15\uc774 \uac10\ud788 \ud56d\ud574\ud558\uc9c0 \ubabb\ud558\ub294 \ubbf8\uc9c0\uc758 \ud574\uc548\uacfc \uac15\uc744 \ud0d0\ud5d8\ud558\ub294\ub370 \ub531 \ub4e4\uc5b4\ub9de\uc558\ub2e4. \uce90\ub7ec\ubc38\uc740 \ub610\ud55c \uac70\uce5c \ub300\uc11c\uc591\uc744 \ud56d\ud574\ud558\ub294 \ub370\ub3c4 \ubb34\ub9ac\uac00 \uc5c6\uc744 \ub9cc\ud07c \ud6cc\ub96d\ud55c \uc6d0\uc591\uc120\ubc15\uc774\uc5c8\ub2e4. \ud06c\ub9ac\uc2a4\ud1a0\ud37c \ucf5c\ub7fc\ubc84\uc2a4\uc758 \uae30\ud568 \uc0b0\ud0c0 \ub9c8\ub9ac\uc544\ub294 \uce74\ub77d\uc774\uc5c8\uc9c0\ub9cc \ub098\uba38\uc9c0 \ub450 \ucc99 \ud540\ud0c0\uc640 \ub2c8\ub098\ub294 \uce90\ub7ec\ubca8\uc774\uc5c8\ub2e4.",
    "strategy": "\uce90\ub7ec\ubca8\uc740 \ubb38\uba85\uc758 \ud574\uad70\ub825\uc5d0 \ud070 \ubcf4\ud0ec\uc774 \ub429\ub2c8\ub2e4. \uadfc\uc811 \uacf5\uaca9 \uc720\ub2db\uc73c\ub85c, \uc0bc\ub2e8\ub178\uc120\ubcf4\ub2e4 \uac15\ud558\uace0 \ube60\ub974\uba70, \uc2ec\ud574 \ud0c0\uc77c\uc5d0\ub3c4 \ub4e4\uc5b4\uac08 \uc218 \uc788\uc2b5\ub2c8\ub2e4. \uce90\ub7ec\ubca8\uc758 \ube60\ub978 \uc18d\ub3c4\ub294 \uc801\uc758 \ud574\uc0c1 \uc720\ub2db\uc774 \uadfc\uc811 \uacf5\uaca9\uc744 \uac00\ud558\uae30 \uc804 \uba40\ub9ac \ub5a8\uc5b4\uc9c8 \uc218 \uc788\ub294 \uae30\ub3d9\ub825\uc744 \ubcf4\uac15\ud574 \uc90d\ub2c8\ub2e4. \uce90\ub7ec\ubca8\uc740 \uc2dc\uc57c\ub3c4 \uad49\uc7a5\ud788 \ub113\uc5b4\uc11c \uac8c\uc784 \uc911\ubc18 \ud574\uad70\uc758 \ub208\uacfc \uadc0\uac00 \ub418\uc5b4\uc90d\ub2c8\ub2e4. \uc2dc\uc57c \ubcf4\ub108\uc2a4\ub294 \uce90\ub7ec\ubca8\uc774 \uad6c\ucd95\ud568\uc73c\ub85c \uc5c5\uadf8\ub808\uc774 \ub418\uba74 \uc0ac\ub77c\uc9c0\uac8c \ub429\ub2c8\ub2e4.",
    "movement": 4,
    "cost": {
        "production": 120,
        "faith": 0
    },
    "prereq_tech": {
        "name": "\ucc9c\ubb38\ud559",
        "url": "https://eyefyre.github.io/civvapi/v1/kr/tech/astronomy.json"
    },
    "free_promotions": [
        {
            "name": "\uc2dc\uc57c \uc99d\uac00(1)",
            "url": "https://eyefyre.github.io/civvapi/v1/kr/promotions/extra_sight_(1).json"
        },
        {
            "name": "\uadfc\uc811\uc804 \ud68c\ud53c",
            "url": "https://eyefyre.github.io/civvapi/v1/kr/promotions/withdraw_before_melee.json"
        }
    ]
}