{
    "id": 11,
    "name": "\uc7ac\ubc30\uc9c0",
    "game_info": "\uc7ac\ubc30\uc9c0\ub294 \ub18d\uc7a5\uc744 \uc9c0\uce6d\ud558\ub294 \uace0\uae09\uc2a4\ub7ec\uc6b4 \uc774\ub984\uc785\ub2c8\ub2e4. \ubcf4\ud1b5 \uc7ac\ubc30\uc9c0\ub294 \uc900 \uc5f4\ub300\uc9c0\uc5ed\uc774\ub098 \uc5f4\ub300\uc9c0\uc5ed\uc5d0 \uc788\ub294 \ub300\uaddc\ubaa8 \ud1a0\uc9c0\uc5d0 \uc801\uc6a9\ub418\uba70 \ud2b9\ud788 \ud604\uc9c0 \uc18c\ube44\uc6a9 \uc791\ubb3c\uc774 \uc544\ub2c8\ub77c \uc218\ucd9c\uc6a9 \uc791\ubb3c\uc744 \uc7ac\ubc30\ud558\ub294 \ub18d\uc7a5\uc744 \ub9d0\ud569\ub2c8\ub2e4. \uc774 \ub2e8\uc5b4\ub294 \ubbf8\uad6d\uacfc \uce74\ub9ac\ube0c \ud574\uc758 \ub178\uc608 \uc81c\ub3c4\uc640 \uc5f0\uad00\ub418\uc5b4 \uc88b\uc9c0 \uc54a\uc740 \ub258\uc559\uc2a4\ub97c \ub744\uace0 \uc788\uc9c0\ub9cc \uc790\uc720\ub85c\uc6b4 \uc77c\uafbc\uc744 \uace0\uc6a9\ud574 \uc798 \uc6b4\uc601\ub418\uace0 \uc788\ub294 \uc7ac\ubc30\uc9c0\uc5d0\ub294 \uc5b4\ub5a0\ud55c \ub098\uc05c \uc810\ub3c4 \uc5c6\uc2b5\ub2c8\ub2e4.",
    "icon": "https://eyefyre.github.io/civvapi/images/improvement_icons/\uc7ac\ubc30\uc9c0.png",
    "nearby_mountain_bonus": {
        "food": null
    },
    "can_be_built_on": [],
    "improves_resources": [
        {
            "name": "\ubc14\ub098\ub098",
            "url": "https://eyefyre.github.io/civvapi/v1/kr/resources/bananas.json"
        },
        {
            "name": "\uc5fc\ub8cc",
            "url": "https://eyefyre.github.io/civvapi/v1/kr/resources/dyes.json"
        },
        {
            "name": "\ube44\ub2e8",
            "url": "https://eyefyre.github.io/civvapi/v1/kr/resources/silk.json"
        },
        {
            "name": "\ud5a5\uc2e0\ub8cc",
            "url": "https://eyefyre.github.io/civvapi/v1/kr/resources/spices.json"
        },
        {
            "name": "\uc124\ud0d5",
            "url": "https://eyefyre.github.io/civvapi/v1/kr/resources/sugar.json"
        },
        {
            "name": "\ubaa9\ud654",
            "url": "https://eyefyre.github.io/civvapi/v1/kr/resources/cotton.json"
        },
        {
            "name": "\uc640\uc778",
            "url": "https://eyefyre.github.io/civvapi/v1/kr/resources/wine.json"
        },
        {
            "name": "\ud5a5",
            "url": "https://eyefyre.github.io/civvapi/v1/kr/resources/incense.json"
        },
        {
            "name": "\uac10\uade4",
            "url": "https://eyefyre.github.io/civvapi/v1/kr/resources/citrus.json"
        },
        {
            "name": "\ucf54\ucf54\uc544",
            "url": "https://eyefyre.github.io/civvapi/v1/kr/resources/cocoa.json"
        }
    ],
    "prereq_tech": {
        "name": "\uc5ed\ubc95",
        "url": "https://eyefyre.github.io/civvapi/v1/kr/tech/calendar.json"
    },
    "required_civ": null,
    "yields": {
        "gold": 0,
        "production": 0,
        "science": 0,
        "culture": 0,
        "food": 0,
        "faith": 0,
        "happiness": 0
    }
}