{
    "id": 48,
    "name": "Arkebuzerzy|Arkebuzer\u00f3w|Arkebuzerom|Arkebuzer\u00f3w",
    "icon": "https://eyefyre.github.io/civvapi/images/unit_icons/musketman.png",
    "game_info": "Pierwsza jednostka z broni\u0105 paln\u0105 w grze. Do\u015b\u0107 tania i silna.",
    "historical_info": "Muszkiet to bro\u0144 z zamkiem ska\u0142kowym, \u0142adowana przez charakterystyczn\u0105, d\u0142ug\u0105 luf\u0119. Strza\u0142 oddawany jest z ramienia. Muszkiet by\u0142 l\u017cejszy i celniejszy od poprzedniego przedstawiciela broni palnej, czyli arkebuza. W XVIII wieku u\u017cywano go powszechnie na niemal wszystkich europejskich polach bitew. Po wyposa\u017ceniu w bagnet, muszkiet stawa\u0142 si\u0119 r\u00f3wnie\u017c skuteczn\u0105 broni\u0105 do walki w zwarciu, co spowodowa\u0142o znikni\u0119cie formacji pikinier\u00f3w. Archetypem muszkietu jest angielski \u201eBrown Bess\u201d, kt\u00f3ry by\u0142 w u\u017cyciu od 1722 do 1838 roku. Korzysta\u0142y te\u017c z niego strony walcz\u0105ce ze sob\u0105 podczas Ameryka\u0144skiej Rewolucji.",
    "strategy": "Arkebuzerzy to pierwsza jednostka z broni\u0105 prochow\u0105 w grze, zast\u0119puj\u0105ca starsze jednostki piechur\u00f3w - tarczownik\u00f3w, pikinier\u00f3w, itp. Nie jest to jednak jednostka strzelaj\u0105ca i nie mo\u017ce atakowa\u0107 przeciwnika znajduj\u0105cego si\u0119 w odleg\u0142o\u015bci wi\u0119kszej ni\u017c jeden heks.",
    "movement": 2,
    "cost": {
        "production": 150,
        "faith": 300
    },
    "prereq_tech": {
        "name": "Proch strzelniczy|Prochu strzelniczego|Prochowi strzelniczemu|Proch strzelniczy",
        "url": "https://eyefyre.github.io/civvapi/v1/pl/tech/gunpowder.json"
    },
    "free_promotions": []
}